LittleSnowFox/__init__.py
LittleSnowFox/kl_settings.py
LittleSnowFox/R_processing/__init__.py
LittleSnowFox/kl_sample/__init__.py
LittleSnowFox/kl_sample/paper_sample.py
LittleSnowFox/omic_functions/CellColorMapPlot.py
LittleSnowFox/omic_functions/CellColorMapPlot2.py
LittleSnowFox/omic_functions/Download.py
LittleSnowFox/omic_functions/__init__.py
LittleSnowFox/omic_functions/clone_analysis.py
LittleSnowFox/omic_functions/datasets.py
LittleSnowFox/omic_functions/hf.py
LittleSnowFox/omic_functions/logging.py
LittleSnowFox/omic_functions/matrix.py
LittleSnowFox/omic_functions/pl.py
LittleSnowFox/omic_functions/pp.py
LittleSnowFox/omic_functions/settings.py
LittleSnowFox/omic_functions/simulate.py
LittleSnowFox/omic_functions/tl.py
LittleSnowFox/omic_functions/help_functions/__init__.py
LittleSnowFox/omic_functions/help_functions/_docs.py
LittleSnowFox/omic_functions/help_functions/_help_functions_CoSpar.py
LittleSnowFox/omic_functions/plotting/__init__.py
LittleSnowFox/omic_functions/plotting/_clone.py
LittleSnowFox/omic_functions/plotting/_gene.py
LittleSnowFox/omic_functions/plotting/_map.py
LittleSnowFox/omic_functions/plotting/_utils.py
LittleSnowFox/omic_functions/preprocessing/__init__.py
LittleSnowFox/omic_functions/preprocessing/_preprocessing.py
LittleSnowFox/omic_functions/tmap/__init__.py
LittleSnowFox/omic_functions/tmap/_tmap_core.py
LittleSnowFox/omic_functions/tmap/_utils.py
LittleSnowFox/omic_functions/tmap/map_reconstruction.py
LittleSnowFox/omic_functions/tmap/optimal_transport.py
LittleSnowFox/omic_functions/tool/__init__.py
LittleSnowFox/omic_functions/tool/_clone.py
LittleSnowFox/omic_functions/tool/_gene.py
LittleSnowFox/omic_functions/tool/_map.py
LittleSnowFox/omic_functions/tool/_utils.py
LittleSnowFox/preprocessing/__init__.py
LittleSnowFox/preprocessing/kl_pre.py
LittleSnowFox/preprocessing/kl_similar_matrix.py
LittleSnowFox/workcatalogue/__init__.py
LittleSnowFox/workcatalogue/kl_load.py
littlesnowfox-0.2.3.3.dist-info/METADATA
littlesnowfox-0.2.3.3.dist-info/WHEEL
littlesnowfox-0.2.3.3.dist-info/top_level.txt
littlesnowfox-0.2.3.3.dist-info/RECORD
